LICENSE
MANIFEST.in
README.md
requirements.txt
setup.py
ddf_library/__init__.py
ddf_library/config.py
ddf_library/context.py
ddf_library/ddf.py
ddf_library/ddf_base.py
ddf_library/ddf_model.py
ddf_library/groupby.py
ddf_library/utils.py
ddf_library/functions/__init__.py
ddf_library/functions/geo.py
ddf_library/functions/graph.py
ddf_library/functions/etl/__init__.py
ddf_library/functions/etl/add_columns.py
ddf_library/functions/etl/aggregation.py
ddf_library/functions/etl/attributes_changer.py
ddf_library/functions/etl/balancer.py
ddf_library/functions/etl/clean_missing.py
ddf_library/functions/etl/cross_join.py
ddf_library/functions/etl/distinct.py
ddf_library/functions/etl/drop.py
ddf_library/functions/etl/except_all.py
ddf_library/functions/etl/explode.py
ddf_library/functions/etl/filter.py
ddf_library/functions/etl/hash_partitioner.py
ddf_library/functions/etl/intersect.py
ddf_library/functions/etl/join.py
ddf_library/functions/etl/map.py
ddf_library/functions/etl/parallelize.py
ddf_library/functions/etl/range_partitioner.py
ddf_library/functions/etl/read_data.py
ddf_library/functions/etl/repartition.py
ddf_library/functions/etl/replace_values.py
ddf_library/functions/etl/sample.py
ddf_library/functions/etl/save_data.py
ddf_library/functions/etl/select.py
ddf_library/functions/etl/sort.py
ddf_library/functions/etl/split.py
ddf_library/functions/etl/subtract.py
ddf_library/functions/etl/take.py
ddf_library/functions/etl/union.py
ddf_library/functions/geo_lib/__init__.py
ddf_library/functions/geo_lib/geo_within.py
ddf_library/functions/geo_lib/read_shapefile.py
ddf_library/functions/geo_lib/st_dbscan.py
ddf_library/functions/graph_lib/__init__.py
ddf_library/functions/graph_lib/page_rank.py
ddf_library/functions/ml/__init__.py
ddf_library/functions/ml/classification.py
ddf_library/functions/ml/clustering.py
ddf_library/functions/ml/evaluation.py
ddf_library/functions/ml/feature.py
ddf_library/functions/ml/fpm.py
ddf_library/functions/ml/regression.py
ddf_pycompss.egg-info/PKG-INFO
ddf_pycompss.egg-info/SOURCES.txt
ddf_pycompss.egg-info/dependency_links.txt
ddf_pycompss.egg-info/requires.txt
ddf_pycompss.egg-info/top_level.txt