Metadata-Version: 2.1
Name: ddf-pycompss
Version: 0.4
Summary: A PyCOMPSs library for Big Data scenarios.
Home-page: https://github.com/eubr-bigsea/Compss-Python
Author: Lucas Miguel Ponce
Author-email: lucasmsp@dcc.ufmg.br
License: Apache License, Version 2.0
Platform: Linux
Classifier: Programming Language :: Python :: 3
Classifier: Programming Language :: Python :: 3.6
Classifier: License :: OSI Approved :: Apache Software License
Classifier: Operating System :: POSIX :: Linux
Classifier: Topic :: Software Development :: Libraries
Classifier: Topic :: Software Development :: Libraries :: Python Modules
Classifier: Topic :: System :: Distributed Computing
